README.md
setup.cfg
setup.py
NSRP/Calibration.py
NSRP/HiperParams.py
NSRP/MathematicalPropertiesNSRP.py
NSRP/PSOMdJ.py
NSRP/Simulation.py
NSRP/Statistics.py
NSRP/__init__.py
NSRP/inputs_simulation.py
NSRP/libs_NSRP.py
NSRP/outputs_simulation.py
NSRP/parameters_calibration.py
NSRP/utils.py
STNSRP/__init__.py
STNSRPM.egg-info/PKG-INFO
STNSRPM.egg-info/SOURCES.txt
STNSRPM.egg-info/dependency_links.txt
STNSRPM.egg-info/requires.txt
STNSRPM.egg-info/top_level.txt