Metadata-Version: 2.1
Name: STNSRPM
Version: 0.0.6
Summary: 🌎 Scripts and information to synthetic generation of precipitation based on Point Processes.
Home-page: https://github.com/navass11/STNSRPM/tree/Crear-ejecutable
Author: Javier Diez Sierra
Author-email: javier.diez@unican.es
Maintainer: Manuel del Jesus Peñil
Maintainer-email: manuel.deljesus@unican.es
License: UNKNOWN
Platform: UNKNOWN
Requires-Python: >=3.7, <4
Provides-Extra: plotting
